coinor.grumpy-0.95.1-py3.8-nspkg.pth
coinor/grumpy/BBTree.py
coinor/grumpy/BranchAndBound.py
coinor/grumpy/__init__.py
coinor/grumpy/__main__.py
coinor/grumpy/forecasting.py
coinor/grumpy/polyhedron2D.py
coinor/grumpy/examples/BBVis.py
coinor/grumpy/examples/DecompVis.py
coinor/grumpy/examples/Dippy.py
coinor/grumpy/examples/DisplayPolyhedron.py
coinor/grumpy/examples/DisplayPolyhedronAndSolveLP.py
coinor/grumpy/examples/GMI-Example.py
coinor/grumpy/examples/InverseProblemVisualization.py
coinor/grumpy/examples/LP1.py
coinor/grumpy/examples/LP2.py
coinor/grumpy/examples/LP3.py
coinor/grumpy/examples/LP4.py
coinor/grumpy/examples/LP5.py
coinor/grumpy/examples/LP6.py
coinor/grumpy/examples/LP7.py
coinor/grumpy/examples/LP8.py
coinor/grumpy/examples/LP9.py
coinor/grumpy/examples/__init__.py
coinor/grumpy/examples/generators.py
coinor/grumpy/examples/p0201_GLPK.vbc
coinor/grumpy/examples/p0201_SYMPHONY.vbc
coinor.grumpy-0.95.1.dist-info/AUTHORS
coinor.grumpy-0.95.1.dist-info/LICENSE
coinor.grumpy-0.95.1.dist-info/METADATA
coinor.grumpy-0.95.1.dist-info/WHEEL
coinor.grumpy-0.95.1.dist-info/namespace_packages.txt
coinor.grumpy-0.95.1.dist-info/top_level.txt
coinor.grumpy-0.95.1.dist-info/RECORD
