Metadata-Version: 2.1
Name: coinor.grumpy
Version: 0.95.1
Summary: Graphics for Understanding Mathematical Programming (GrUMPy)
Home-page: https://github.com/tkralphs/GrUMPy/
Author: Aykut Bulut, Ted Ralphs
Author-email: ted@lehigh.edu
License: Eclipse Public License
Platform: UNKNOWN
Requires-Dist: coinor.gimpy (>=2.1.0)
Requires-Dist: pulp
